{
  "logicalTable": {
    "name": "Bbil Fact Bookings",
    "type": "FACT",
    "logicalColumns": [ {
        "name": "# Of Billtocust Id",
        "dataType": "DOUBLE",
        "logicalColumnSource": {
          "derivedFrom": "PHYSICAL_COLUMNS",
          "physicalMappings": [ {
              "logicalTableSource": "Bbil Fact Bookings",
              "physicalExpression": {
                "expressionTemplate": "%1",
                "expressionObjects": [
                  "physicalColumn:Y01 - Custom Demo Datasets.BBILL.BBIL_FACT_BOOKINGS.BILLTOCUST_ID"
                ]
              }
            }
          ]
        },
        "aggregation": {
          "rule": "BASED_ON_DIMENSION",
          "dimensionBasedRules": [ {
              "dimension": "OTHER",
              "rule": "COUNT_DISTINCT"
            }
          ]
        }
      },
      {
        "name": "Comments",
        "dataType": "VARCHAR",
        "logicalColumnSource": {
          "derivedFrom": "PHYSICAL_COLUMNS",
          "physicalMappings": [ {
              "logicalTableSource": "Bbil Fact Bookings",
              "physicalExpression": {
                "expressionTemplate": "%1",
                "expressionObjects": [
                  "physicalColumn:Y01 - Custom Demo Datasets.BBILL.BBIL_FACT_BOOKINGS.COMMENTS"
                ]
              }
            }
          ]
        }
      },
      {
        "name": "Date Id",
        "dataType": "DOUBLE",
        "logicalColumnSource": {
          "derivedFrom": "PHYSICAL_COLUMNS",
          "physicalMappings": [ {
              "logicalTableSource": "Bbil Fact Bookings",
              "physicalExpression": {
                "expressionTemplate": "%1",
                "expressionObjects": [
                  "physicalColumn:Y01 - Custom Demo Datasets.BBILL.BBIL_FACT_BOOKINGS.DATE_ID"
                ]
              }
            }
          ]
        }
      },
      {
        "name": "Debit Number",
        "dataType": "VARCHAR",
        "logicalColumnSource": {
          "derivedFrom": "PHYSICAL_COLUMNS",
          "physicalMappings": [ {
              "logicalTableSource": "Bbil Fact Bookings",
              "physicalExpression": {
                "expressionTemplate": "%1",
                "expressionObjects": [
                  "physicalColumn:Y01 - Custom Demo Datasets.BBILL.BBIL_FACT_BOOKINGS.DEBIT_NUMBER"
                ]
              }
            }
          ]
        }
      },
      {
        "name": "# Of Endcust Id",
        "dataType": "DOUBLE",
        "logicalColumnSource": {
          "derivedFrom": "PHYSICAL_COLUMNS",
          "physicalMappings": [ {
              "logicalTableSource": "Bbil Fact Bookings",
              "physicalExpression": {
                "expressionTemplate": "%1",
                "expressionObjects": [
                  "physicalColumn:Y01 - Custom Demo Datasets.BBILL.BBIL_FACT_BOOKINGS.ENDCUST_ID"
                ]
              }
            }
          ]
        },
        "aggregation": {
          "rule": "BASED_ON_DIMENSION",
          "dimensionBasedRules": [ {
              "dimension": "OTHER",
              "rule": "COUNT_DISTINCT"
            }
          ]
        }
      },
      {
        "name": "Ext Amount",
        "dataType": "DOUBLE",
        "logicalColumnSource": {
          "derivedFrom": "PHYSICAL_COLUMNS",
          "physicalMappings": [ {
              "logicalTableSource": "Bbil Fact Bookings",
              "physicalExpression": {
                "expressionTemplate": "%1",
                "expressionObjects": [
                  "physicalColumn:Y01 - Custom Demo Datasets.BBILL.BBIL_FACT_BOOKINGS.EXT_AMOUNT"
                ]
              }
            }
          ]
        },
        "aggregation": {
          "rule": "BASED_ON_DIMENSION",
          "dimensionBasedRules": [ {
              "dimension": "OTHER",
              "rule": "SUM"
            }
          ]
        }
      },
      {
        "name": "Line Number",
        "dataType": "VARCHAR",
        "logicalColumnSource": {
          "derivedFrom": "PHYSICAL_COLUMNS",
          "physicalMappings": [ {
              "logicalTableSource": "Bbil Fact Bookings",
              "physicalExpression": {
                "expressionTemplate": "%1",
                "expressionObjects": [
                  "physicalColumn:Y01 - Custom Demo Datasets.BBILL.BBIL_FACT_BOOKINGS.LINE_NUMBER"
                ]
              }
            }
          ]
        }
      },
      {
        "name": "# Of Order Number",
        "dataType": "VARCHAR",
        "logicalColumnSource": {
          "derivedFrom": "PHYSICAL_COLUMNS",
          "physicalMappings": [ {
              "logicalTableSource": "Bbil Fact Bookings",
              "physicalExpression": {
                "expressionTemplate": "%1",
                "expressionObjects": [
                  "physicalColumn:Y01 - Custom Demo Datasets.BBILL.BBIL_FACT_BOOKINGS.ORDER_NUMBER"
                ]
              }
            }
          ]
        },
        "aggregation": {
          "rule": "BASED_ON_DIMENSION",
          "dimensionBasedRules": [ {
              "dimension": "OTHER",
              "rule": "COUNT_DISTINCT"
            }
          ]
        }
      },
      {
        "name": "# Of Part Id",
        "dataType": "DOUBLE",
        "logicalColumnSource": {
          "derivedFrom": "PHYSICAL_COLUMNS",
          "physicalMappings": [ {
              "logicalTableSource": "Bbil Fact Bookings",
              "physicalExpression": {
                "expressionTemplate": "%1",
                "expressionObjects": [
                  "physicalColumn:Y01 - Custom Demo Datasets.BBILL.BBIL_FACT_BOOKINGS.PART_ID"
                ]
              }
            }
          ]
        },
        "aggregation": {
          "rule": "BASED_ON_DIMENSION",
          "dimensionBasedRules": [ {
              "dimension": "OTHER",
              "rule": "COUNT_DISTINCT"
            }
          ]
        }
      },
      {
        "name": "Po#",
        "dataType": "VARCHAR",
        "logicalColumnSource": {
          "derivedFrom": "PHYSICAL_COLUMNS",
          "physicalMappings": [ {
              "logicalTableSource": "Bbil Fact Bookings",
              "physicalExpression": {
                "expressionTemplate": "%1",
                "expressionObjects": [
                  "physicalColumn:Y01 - Custom Demo Datasets.BBILL.BBIL_FACT_BOOKINGS.PO#"
                ]
              }
            }
          ]
        }
      },
      {
        "name": "Saleschannel Id",
        "dataType": "DOUBLE",
        "logicalColumnSource": {
          "derivedFrom": "PHYSICAL_COLUMNS",
          "physicalMappings": [ {
              "logicalTableSource": "Bbil Fact Bookings",
              "physicalExpression": {
                "expressionTemplate": "%1",
                "expressionObjects": [
                  "physicalColumn:Y01 - Custom Demo Datasets.BBILL.BBIL_FACT_BOOKINGS.SALESCHANNEL_ID"
                ]
              }
            }
          ]
        }
      },
      {
        "name": "Salesrep Id",
        "dataType": "DOUBLE",
        "logicalColumnSource": {
          "derivedFrom": "PHYSICAL_COLUMNS",
          "physicalMappings": [ {
              "logicalTableSource": "Bbil Fact Bookings",
              "physicalExpression": {
                "expressionTemplate": "%1",
                "expressionObjects": [
                  "physicalColumn:Y01 - Custom Demo Datasets.BBILL.BBIL_FACT_BOOKINGS.SALESREP_ID"
                ]
              }
            }
          ]
        }
      },
      {
        "name": "Scenario Id",
        "dataType": "DOUBLE",
        "logicalColumnSource": {
          "derivedFrom": "PHYSICAL_COLUMNS",
          "physicalMappings": [ {
              "logicalTableSource": "Bbil Fact Bookings",
              "physicalExpression": {
                "expressionTemplate": "%1",
                "expressionObjects": [
                  "physicalColumn:Y01 - Custom Demo Datasets.BBILL.BBIL_FACT_BOOKINGS.SCENARIO_ID"
                ]
              }
            }
          ]
        }
      },
      {
        "name": "Unit Price",
        "dataType": "DOUBLE",
        "logicalColumnSource": {
          "derivedFrom": "PHYSICAL_COLUMNS",
          "physicalMappings": [ {
              "logicalTableSource": "Bbil Fact Bookings",
              "physicalExpression": {
                "expressionTemplate": "%1",
                "expressionObjects": [
                  "physicalColumn:Y01 - Custom Demo Datasets.BBILL.BBIL_FACT_BOOKINGS.UNIT_PRICE"
                ]
              }
            }
          ]
        },
        "aggregation": {
          "rule": "BASED_ON_DIMENSION",
          "dimensionBasedRules": [ {
              "dimension": "OTHER",
              "rule": "AVG"
            }
          ]
        }
      },
      {
        "name": "Units",
        "dataType": "DOUBLE",
        "logicalColumnSource": {
          "derivedFrom": "PHYSICAL_COLUMNS",
          "physicalMappings": [ {
              "logicalTableSource": "Bbil Fact Bookings",
              "physicalExpression": {
                "expressionTemplate": "%1",
                "expressionObjects": [
                  "physicalColumn:Y01 - Custom Demo Datasets.BBILL.BBIL_FACT_BOOKINGS.UNITS"
                ]
              }
            }
          ]
        },
        "aggregation": {
          "rule": "BASED_ON_DIMENSION",
          "dimensionBasedRules": [ {
              "dimension": "OTHER",
              "rule": "SUM"
            }
          ]
        }
      }
    ],
    "logicalTableSources": [ {
        "name": "Bbil Fact Bookings",
        "tableMapping": {
          "tables": [
            "physicalTable:Y01 - Custom Demo Datasets.BBILL.BBIL_FACT_BOOKINGS"
          ]
        }
      }
    ]
  }
}
